LICENSE
MANIFEST.in
README.rst
setup.py
typelift/__init__.py
typelift/dewoff.py
typelift.egg-info/PKG-INFO
typelift.egg-info/SOURCES.txt
typelift.egg-info/dependency_links.txt
typelift.egg-info/entry_points.txt
typelift.egg-info/not-zip-safe
typelift.egg-info/requires.txt
typelift.egg-info/top_level.txt