Metadata-Version: 1.1
Name: typelift
Version: 0.2
Summary: Pretty much worthless
Home-page: http://github.com/storborg/typelift
Author: Scott Torborg
Author-email: storborg@gmail.com
License: MIT
Platform: UNKNOWN
Classifier: Programming Language :: Python :: 2.7
